Metadata-Version: 2.1
Name: zs-face-detection
Version: 1.0
Summary: A demo for face detection
Author: wang zs
Author-email: scholar_zswang@163.com
License: UNKNOWN
Platform: UNKNOWN
